mongo_filter_evaluator/__init__.py
mongo_filter_evaluator/base.py
mongo_filter_evaluator/evaluator.py
mongo_filter_evaluator/exceptions.py
mongo_filter_evaluator/types.py
mongo_filter_evaluator/validator.py
mongo_filter_evaluator-1.0.0.dist-info/METADATA
mongo_filter_evaluator-1.0.0.dist-info/RECORD
mongo_filter_evaluator-1.0.0.dist-info/WHEEL
mongo_filter_evaluator-1.0.0.dist-info/top_level.txt
