Metadata-Version: 2.1
Name: mongo-filter-evaluator
Version: 1.0.0
Summary: Evaluator & validator for mongo-like queries
Home-page: https://github.com/zlebnik/mongo_filter_evaluator
Author: Gleb Kovalev
Author-email: gleb@popmechanic.io
License: MIT license
Keywords: mongo_filter_evaluator
Platform: UNKNOWN
Classifier: Development Status :: 2 - Pre-Alpha
Classifier: Intended Audience :: Developers
Classifier: License :: OSI Approved :: MIT License
Classifier: Natural Language :: English
Classifier: Programming Language :: Python :: 2
Classifier: Programming Language :: Python :: 2.7
Classifier: Programming Language :: Python :: 3
Classifier: Programming Language :: Python :: 3.4
Classifier: Programming Language :: Python :: 3.5
Classifier: Programming Language :: Python :: 3.6
